jb_toc_frontend/__init__.py
jb_toc_frontend-2.0.1.data/data/share/jupyter/labextensions/jb-toc-frontend/static/157.c3a4e1ab16de515b08a4.js
jb_toc_frontend-2.0.1.data/data/share/jupyter/labextensions/jb-toc-frontend/static/361.69602d6b5d15ee31acd4.js
jb_toc_frontend-2.0.1.data/data/share/jupyter/labextensions/jb-toc-frontend/static/361.69602d6b5d15ee31acd4.js.LICENSE.txt
jb_toc_frontend-2.0.1.data/data/share/jupyter/labextensions/jb-toc-frontend/static/502.43d0b57197ec43adbc68.js
jb_toc_frontend-2.0.1.data/data/share/jupyter/labextensions/jb-toc-frontend/static/988.ea6ffd18a40a169c067c.js
jb_toc_frontend-2.0.1.data/data/share/jupyter/labextensions/jb-toc-frontend/static/remoteEntry.77382f5fe323733e3d3e.js
jb_toc_frontend-2.0.1.data/data/share/jupyter/labextensions/jb-toc-frontend/static/style.js
jb_toc_frontend-2.0.1.data/data/share/jupyter/labextensions/jb-toc-frontend/static/third-party-licenses.json
jb_toc_frontend-2.0.1.data/data/share/jupyter/labextensions/jb-toc-frontend/install.json
jb_toc_frontend-2.0.1.data/data/share/jupyter/labextensions/jb-toc-frontend/package.json
jb_toc_frontend-2.0.1.dist-info/METADATA
jb_toc_frontend-2.0.1.dist-info/WHEEL
jb_toc_frontend-2.0.1.dist-info/licenses/LICENSE
jb_toc_frontend-2.0.1.dist-info/RECORD
